parallel_execution/__init__.py
parallel_execution/__version__.py
parallel_execution/_parallel_executor.py
parallel_execution-0.1.0a0.dist-info/METADATA
parallel_execution-0.1.0a0.dist-info/WHEEL
parallel_execution-0.1.0a0.dist-info/top_level.txt
parallel_execution-0.1.0a0.dist-info/RECORD
